itk_topologycontrol.libs/libtbb-e046f41a.so.12.9
itk/itkFixTopologyCarveInsidePython.py
itk/itkFixTopologyBasePython.py
itk/itkFixTopologyCarveOutsidePython.py
itk/TopologyControlPython.py
itk/_TopologyControlPython.so
itk/Configuration/TopologyControl_snake_case.py
itk/Configuration/TopologyControlConfig.py
itk_topologycontrol-1.2.0.dist-info/METADATA
itk_topologycontrol-1.2.0.dist-info/RECORD
itk_topologycontrol-1.2.0.dist-info/WHEEL
itk_topologycontrol-1.2.0.dist-info/entry_points.txt
itk_topologycontrol-1.2.0.dist-info/licenses/LICENSE
